{
    "BLACK": "#000000",
    "WHITE": "#ffffff",
    "MILITARY": "#7e7c41",
    "NAVY": "#243d73",
    "WALNUT/SETTER": "#c78242",
    "BLACK/BLACK": "#000000",
    "SILVER": "#c2c7ca",
    "CURRENT RED": "#dd3333",
    "GRAPHITE": "#233667",
    "ATLANTIC BLUE": "#0077ff",
    "NEON GREEN": "#bfe632",
    "BUFFALO PLAID": "6529d7434026558b06b0310ae7e3d4ddcb59786b.png",
    "NATURAL": "#f0e1c9",
    "CHESTNUT": "#c78242",
    "DUSTY PINK": "#e3c8c8",
    "SAGE": "#6e6e0a",
    "TAN": "#c78242",
    "RUSTIC": "#a88f42",
    "BLACK LEATHER": "#000000",
    "CREAM": "#f7f4e4",
    "CUOIO": "#c78242",
    "GREY": "#969899",
    "PINK": "#f714ab",
    "DARK BROWN": "#412023",
    "WOODY": "#814837",
    "SAPPHIRE": "#1b2ede",
    "OX BLOOD": "#612226",
    "PURPLE": "#a897cf",
    "RED": "#dd3333",
    "OLIVE": "#808000",
    "BLACK/WHITE": "#000000|#ffffff",
    "DARK OAK": "#412023",
    "SAND": "#e0cca7",
    "BRONZE STELLARE": "ef8a73691591030830b953d72ac61adcd71dbe8c.png",
    "COBALT": "#0c46cc",
    "BLUE": "#0077ff",
    "BLUE/LIME": "#256fe6|#c3fc60",
    "CURRENT RED/NAVY": "#ed1313|#1829a3",
    "BLACK/MILITARY": "#000000|#2f5717",
    "DARK BROWN/TAUPE": "#59340e|#ccb362",
    "SAND/BLACK": "#e6dec8|#000000",
    "COGNAC/BLACK": "#85611b|#000000",
    "DARK GREY/BLACK": "#6e6363|#000000",
    "BEIGE": "#ede6d1",
    "TESTA DI MORO": "#631414",
    "OLIVE/DARK BROWN": "#2b4d1c|#6e5407",
    "NERO": "#000000",
    "BLACK/KHAKI": "#000000|#2f5717",
    "BIANCO/PRETO": "#ffffff",
    "ANTHRACITE": "#525454",
    "COPPER": "#e09c1d",
    "CHAMPAGNE": "#f5ecd0",
    "WHITE/BLACK": "#000000|#ffffff",
    "CARAMEL": "#a8723b",
    "BLACK ELDORADO": "#363636",
    "TABACCO": "#c2b470",
    "RED/BLACK": "#b80606|#000000",
    "BEIGE STARDUST": "#ede6d1",
    "BLACK STARDUST": "#000000",
    "TAUPE": "#b39688",
    "DARK BROWN/BLACK": "#59340e|#000000",
    "OLIVIA/PRETO": "#355707|#000000",
    "COGNAC": "#c78242",
    "WINE": "#7d1111",
    "GOLD STELLARE": "cf201b4a8d2ada32a4e76d598ff72ffbbe8320cc.png",
    "WHITE MARBLE": "6535962df08fd1a15966ef4be0b911335147d9d0.png",
    "BUFFALO": "46c33fbf5a3333ff970f3ce3bc8c4bf4c00bf283.png",
    "ATLATIC BLUE": "#0000ff",
    "Atlantic Blue": "#0000ff",
    "MARRONE": "#304d08",
    "BLACK PRINT/BLACK": "3b2855b4132f6328b363b8f81208e2e586096cd7.png",
    "COGNAC/BEIGE": "#783f06|#deb892",
    "CHARCOAL IRON": "#555260",
    "BLACK IRON": "#000000",
    "MILITARY/MILITARY CAMO": "#7e7c41|#363410",
    "BLACK/NAVY": "#000000|#243d73",
    "RED/BONE": "#dd3333",
    "SHARK/BONE": "#716f78",
    "RUSTIC/BLACK": "#a88f42",
    "GREY/BLACK": "#6e6363|#000000",
    "SAFARI / WHITE": "#876b51",
    "DARK BROWN/MILITARY": "ca7985ff172b91f93ed84226422d51d616670f8a.png",
    "TAN/CHURCH": "#c78242",
    "BROWN": "#412023",
    "BLACK SUEDE": "#000000",
    "BLACK/TAUPE": "#000000|#b09380",
    "OFFWHITE": "#f5edd7",
    "CUOIO/CREAM": "#c78242",
    "TAUPE/CAMELLO": "#b39688",
    "BLACK STELLARE": "23d5ea764000b2ef3a731c37d844a4ef19a188fc.png",
    "GOLD BEIGE": "d2db70378ce4222b1fdea95db94518541d347c1a.png",
    "TACEY LOW  2.0": "#dd3333",
    "TACEY LOW 2.0": "#dd3333",
    "GOLD METAL": "38b0594c139a9774cdd334a2498fc60fc252861b.png",
    "BLACK METAL": "#000000",
    "BLACK ANTILOPE": "#000000",
    "BEIGE PEARL": "#ede6d1",
    "BLACK PEARL/BEIGE": "#000000",
    "WHITE PEARL": "#ffffff",
    "BLACK PEARL": "#000000",
    "BLACK/BORDEAUX": "#000000|#7d0721",
    "WHITE IRON": "#ffffff",
    "CHARCOAL": "#555260",
    "RED STELLARE": "#9e282b",
    "DARK RED": "#800909",
    "EBONY": "#6b4a3c",
    "ICE": "#dadad8",
    "CHOCOLATE": "#854f04",
    "SHARK": "#716f78",
    "KHAKI": "#b4b8a0",
    "BLACK/GOLD": "#000000|#e6d149",
    "BLACK/ELM BARK": "#000000|#755b0c",
    "BONE": "#dcd5cb",
    "TAUPE/VIOLET": "#b351c9|#b09380",
    "SHARK/TEAL": "#23917b|#716f78",
    "LIGHT ICE/BLACK": "#d6d6d6|#000000",
    "NAVY/TAUPE": "#2d3573|#b39688",
    "OPTICAL WHITE": "#ffffff",
    "BLACK/WHITE/BLACK": "#000000|#ffffff",
    "BRANCO/PRETO": "#f0f0f0|#1c1c1c",
    "NUDE LEATHER": "#dcd5cb",
    "ORANGE": "#db7535",
    "COGNAC/EBONY": "#6b4a3c|#422828",
    "COGNAC/CHESTNUT": "#c78242",
    "BLACK/BLUE/DARK TEAL": "#000000|#2f5f8f",
    "ASH/GRIGIO": "#9c8e8e",
    "ANTHRACITE/PRETO": "#525454",
    "GOLDEN": "#fcdc0d",
    "MAGNOLIA": "#c393c7",
    "TEAL": "#228b99",
    "CAMEL": "#c78242",
    "ECRU SUEDE": "#ded7c1",
    "MINK SUEDE": "#9e7162",
    "NEON LIME": "#36e833",
    "NEON PINK": "#f714ab",
    "TOFFEE": "#ccae85",
    "CREME SUEDE": "#e3dccc",
    "CASTANHO": "#7d5341",
    "WHISKEY": "#d98032",
    "QUARZO ROSA": "#ebaeb3",
    "BROWN/WHITE": "#573c2d|#ffffff",
    "GOLD METAL STELLARE": "02b549f4ba48509fa0b0dc082cf59b4a86dc7f13.png",
    "BORDEAUX": "#7d0721",
    "COGNAC/NAVY": "#85611b|#0a3273",
    "CAMOFLAGE": "#000000|#384f2a",
    "BLACK/GREY CAMO": "#000000|#243d73",
    "BLACK/VINTAGE PRINT": "afaad33768238db872c8c7fed90462f233b4d576.png",
    "RED/BUFFALO PLAID": "031dca7b49074cbc91aecfa7df3532b6d1922899.png",
    "OLIVE CAMO": "ca8d7bd6f9cfdfd0bbe2fcc1a26096ad3cb9d3e1.png",
    "RED/BONE/MULTI": "#f0efdd|#d11313",
    "BLACK/BONE/MULTI": "#f0efdd|#000000",
    "GINGER": "#c78242",
    "WHITE STELLARE": "#ffffff",
    "BLACK CAMO": "#000000",
    "CURRENT RED/BLACK": "#ed1313|#000000",
    "Camoflage/Black": "#000000|#384f2a",
    "OXBLOOD": "#612226",
    "OFF WHITE": "#d7d7d7",
    "MULTI COLOR": "#000000",
    "DARK GREY": "#555260",
    "LAMB": "#c9bfa6",
    "LIGHT GREY": "#c2c7ca",
    "TAUPE/BLACK": "#b09380|#000000"
}